{
  "schemaVersion": 1,
  "id": "worleycaves",
  "version": "${version}",
  "name": "Worley's Caves",
  "description": "Cave generation with Worley noise!",
  "authors": [
    "Tesseract"
  ],
  "contact": {
    "homepage": "",
    "sources": ""
  },
  "license": "MIT",
  "environment": "*",
  "entrypoints": {
    "main": [
      "cn.tesseract.worleycaves.Main"
    ]
  },
  "mixins": [
    "worleycaves.mixins.json"
  ],
  "depends": {
    "fabricloader": ">=0.14.19",
    "minecraft": "1.8.9"
  },
  "suggests": {
    "another-mod": "*"
  }
}
